solgpt/__init__.py
solgpt/downloader.py
solgpt-0.3.dist-info/LICENSE
solgpt-0.3.dist-info/METADATA
solgpt-0.3.dist-info/WHEEL
solgpt-0.3.dist-info/entry_points.txt
solgpt-0.3.dist-info/top_level.txt
solgpt-0.3.dist-info/RECORD
